odoo8_addon_sale_payment_term_interest-8.0.1.0.0.99.dev29-py3.8-nspkg.pth
odoo_addons/sale_payment_term_interest/README.rst
odoo_addons/sale_payment_term_interest/__init__.py
odoo_addons/sale_payment_term_interest/__openerp__.py
odoo_addons/sale_payment_term_interest/data/product_data.xml
odoo_addons/sale_payment_term_interest/i18n/ca.po
odoo_addons/sale_payment_term_interest/i18n/de.po
odoo_addons/sale_payment_term_interest/i18n/es.po
odoo_addons/sale_payment_term_interest/i18n/es_ES.po
odoo_addons/sale_payment_term_interest/i18n/fi.po
odoo_addons/sale_payment_term_interest/i18n/fr.po
odoo_addons/sale_payment_term_interest/i18n/hr.po
odoo_addons/sale_payment_term_interest/i18n/hu.po
odoo_addons/sale_payment_term_interest/i18n/it.po
odoo_addons/sale_payment_term_interest/i18n/nl.po
odoo_addons/sale_payment_term_interest/i18n/nl_NL.po
odoo_addons/sale_payment_term_interest/i18n/pt_BR.po
odoo_addons/sale_payment_term_interest/i18n/ro.po
odoo_addons/sale_payment_term_interest/i18n/sale_payment_term_interest.pot
odoo_addons/sale_payment_term_interest/i18n/sk.po
odoo_addons/sale_payment_term_interest/i18n/sl.po
odoo_addons/sale_payment_term_interest/i18n/tr.po
odoo_addons/sale_payment_term_interest/i18n/tr_TR.po
odoo_addons/sale_payment_term_interest/i18n/zh_CN.po
odoo_addons/sale_payment_term_interest/model/__init__.py
odoo_addons/sale_payment_term_interest/model/account_payment_term.py
odoo_addons/sale_payment_term_interest/model/sale_order.py
odoo_addons/sale_payment_term_interest/static/description/icon.png
odoo_addons/sale_payment_term_interest/tests/__init__.py
odoo_addons/sale_payment_term_interest/tests/test_payment_term.py
odoo_addons/sale_payment_term_interest/tests/test_sale_order.py
odoo_addons/sale_payment_term_interest/view/account_payment_term_view.xml
odoo_addons/sale_payment_term_interest/view/sale_order_view.xml
odoo8_addon_sale_payment_term_interest-8.0.1.0.0.99.dev29.dist-info/METADATA
odoo8_addon_sale_payment_term_interest-8.0.1.0.0.99.dev29.dist-info/WHEEL
odoo8_addon_sale_payment_term_interest-8.0.1.0.0.99.dev29.dist-info/namespace_packages.txt
odoo8_addon_sale_payment_term_interest-8.0.1.0.0.99.dev29.dist-info/top_level.txt
odoo8_addon_sale_payment_term_interest-8.0.1.0.0.99.dev29.dist-info/RECORD
